snapshot_queries/__init__.py
snapshot_queries/optional_dependencies.py
snapshot_queries/query.py
snapshot_queries/query_list.py
snapshot_queries/sliceable_list.py
snapshot_queries/snapshot_queries.py
snapshot_queries/stacktrace.py
snapshot_queries/timedelta.py
snapshot_queries/testing/__init__.py
snapshot_queries/testing/assert_queries_match_mixin.py
snapshot_queries/testing/default_query_filter.py
snapshot_queries/testing/default_query_rewrite.py
snapshot_queries/testing/pytest_plugin.py
snapshot_queries/testing/snapshot_queries_django_test_case.py
snapshot_queries/testing/snapshot_queries_test_case.py
snapshot_queries-0.5.3.dist-info/LICENSE.txt
snapshot_queries-0.5.3.dist-info/METADATA
snapshot_queries-0.5.3.dist-info/WHEEL
snapshot_queries-0.5.3.dist-info/entry_points.txt
snapshot_queries-0.5.3.dist-info/top_level.txt
snapshot_queries-0.5.3.dist-info/RECORD
