Metadata-Version: 2.1
Name: snapshot-queries
Version: 0.5.3
Summary: A tool for capturing queries executed in Django and SQLAlchemy
Home-page: https://github.com/cedar-team/snapshot-queries
Author: Cedar
Author-email: "support@cedar.com"
License: UNKNOWN
Keywords: queries,testing,snapshots,orm,sql
Platform: UNKNOWN
Classifier: Programming Language :: Python :: 3
Classifier: License :: OSI Approved :: MIT License
Classifier: Operating System :: OS Independent
License-File: LICENSE.txt
Requires-Dist: sqlparse (>=0.4.1)
Requires-Dist: attrs (>=20.3.0)
Requires-Dist: pygments (>=2.8.1)
Provides-Extra: development
Requires-Dist: snapshottest (==0.5.1) ; extra == 'development'
Requires-Dist: pytest (==7.1.1) ; extra == 'development'
Requires-Dist: psycopg2-binary (==2.8.6) ; extra == 'development'
Requires-Dist: ipdb ; extra == 'development'
Requires-Dist: pre-commit ; extra == 'development'
Provides-Extra: linting
Requires-Dist: black (==22.3.0) ; extra == 'linting'
Requires-Dist: flake8 (==4.0.1) ; extra == 'linting'
Requires-Dist: isort (==5.10.1) ; extra == 'linting'
Provides-Extra: snapshottest
Requires-Dist: snapshottest ; extra == 'snapshottest'
